{"Routes":[{"SwaggerKey":"mstwo.svc","DownstreamPathTemplate":"/api/{everything}","UpstreamPathTemplate":"/api/mstwo.svc/{everything}","UpstreamHttpMethod":[],"DownstreamHttpMethod":null,"AddHeadersToRequest":{},"UpstreamHeaderTransform":{},"DownstreamHeaderTransform":{},"AddClaimsToRequest":{},"RouteClaimsRequirement":{},"AddQueriesToRequest":{},"ChangeDownstreamPathTemplate":{},"RequestIdKey":null,"FileCacheOptions":{"TtlSeconds":0,"Region":null},"RouteIsCaseSensitive":false,"ServiceName":"mstwo.svc","ServiceNamespace":null,"DownstreamScheme":null,"QoSOptions":{"ExceptionsAllowedBeforeBreaking":0,"DurationOfBreak":0,"TimeoutValue":0},"LoadBalancerOptions":{"Type":null,"Key":null,"Expiry":0},"RateLimitOptions":{"ClientWhitelist":[],"EnableRateLimiting":false,"Period":null,"PeriodTimespan":0.0,"Limit":0},"AuthenticationOptions":{"AuthenticationProviderKey":null,"AllowedScopes":[]},"HttpHandlerOptions":{"AllowAutoRedirect":false,"UseCookieContainer":false,"UseTracing":false,"UseProxy":true,"MaxConnectionsPerServer":2147483647},"DownstreamHostAndPorts":[],"UpstreamHost":null,"Key":null,"DelegatingHandlers":[],"Priority":1,"Timeout":0,"DangerousAcceptAnyServerCertificateValidator":false,"SecurityOptions":{"IPAllowedList":[],"IPBlockedList":[]},"DownstreamHttpVersion":null},{"SwaggerKey":"msone.svc","DownstreamPathTemplate":"/api/{everything}","UpstreamPathTemplate":"/api/msone.svc/{everything}","UpstreamHttpMethod":[],"DownstreamHttpMethod":null,"AddHeadersToRequest":{},"UpstreamHeaderTransform":{},"DownstreamHeaderTransform":{},"AddClaimsToRequest":{},"RouteClaimsRequirement":{},"AddQueriesToRequest":{},"ChangeDownstreamPathTemplate":{},"RequestIdKey":null,"FileCacheOptions":{"TtlSeconds":0,"Region":null},"RouteIsCaseSensitive":false,"ServiceName":"msone.svc","ServiceNamespace":null,"DownstreamScheme":null,"QoSOptions":{"ExceptionsAllowedBeforeBreaking":0,"DurationOfBreak":0,"TimeoutValue":0},"LoadBalancerOptions":{"Type":null,"Key":null,"Expiry":0},"RateLimitOptions":{"ClientWhitelist":[],"EnableRateLimiting":false,"Period":null,"PeriodTimespan":0.0,"Limit":0},"AuthenticationOptions":{"AuthenticationProviderKey":null,"AllowedScopes":[]},"HttpHandlerOptions":{"AllowAutoRedirect":false,"UseCookieContainer":false,"UseTracing":false,"UseProxy":true,"MaxConnectionsPerServer":2147483647},"DownstreamHostAndPorts":[],"UpstreamHost":null,"Key":null,"DelegatingHandlers":[],"Priority":1,"Timeout":0,"DangerousAcceptAnyServerCertificateValidator":false,"SecurityOptions":{"IPAllowedList":[],"IPBlockedList":[]},"DownstreamHttpVersion":null}],"DynamicRoutes":[],"Aggregates":[],"GlobalConfiguration":{"RequestIdKey":null,"ServiceDiscoveryProvider":{"Scheme":null,"Host":null,"Port":0,"Type":"AppConfiguration","Token":null,"ConfigurationKey":null,"PollingInterval":0,"Namespace":null},"RateLimitOptions":{"ClientIdHeader":"ClientId","QuotaExceededMessage":null,"RateLimitCounterPrefix":"ocelot","DisableRateLimitHeaders":false,"HttpStatusCode":429},"QoSOptions":{"ExceptionsAllowedBeforeBreaking":0,"DurationOfBreak":0,"TimeoutValue":0},"BaseUrl":null,"LoadBalancerOptions":{"Type":null,"Key":null,"Expiry":0},"DownstreamScheme":null,"HttpHandlerOptions":{"AllowAutoRedirect":false,"UseCookieContainer":false,"UseTracing":false,"UseProxy":true,"MaxConnectionsPerServer":2147483647},"DownstreamHttpVersion":null},"SwaggerEndPoints":[{"Key":"msone.svc","VersionPlaceholder":"{version}","KeyToPath":"msone.svc","Config":[{"Name":"ms one API","Version":"v1","Url":null,"Service":{"Name":"msone.svc","Path":"/swagger/v1/swagger.json"}}],"HostOverride":null,"TransformByOcelotConfig":true},{"Key":"mstwo.svc","VersionPlaceholder":"{version}","KeyToPath":"mstwo.svc","Config":[{"Name":"ms two API","Version":"v1","Url":null,"Service":{"Name":"mstwo.svc","Path":"/swagger/v1/swagger.json"}}],"HostOverride":null,"TransformByOcelotConfig":true}]}